lcdata/__init__.py
lcdata/dataset.py
lcdata/lightcurve.py
lcdata/schema.py
lcdata/utils.py
lcdata/datasets/__init__.py
lcdata/datasets/vav2020_table1_patched.tex.bz2
lcdata/scripts/__init__.py
lcdata/scripts/lcdata_download_plasticc.py
lcdata/scripts/lcdata_download_ps1.py
lcdata/tests/__init__.py
lcdata/tests/test_dataset.py
lcdata/tests/test_lightcurve.py
lcdata/tests/test_schema.py
lcdata/tests/test_utils.py
lcdata-1.1.2.dist-info/LICENSE
lcdata-1.1.2.dist-info/METADATA
lcdata-1.1.2.dist-info/WHEEL
lcdata-1.1.2.dist-info/entry_points.txt
lcdata-1.1.2.dist-info/top_level.txt
lcdata-1.1.2.dist-info/RECORD
