Metadata-Version: 2.1
Name: lcdata
Version: 1.1.2
Summary: lcdata: Tools for manipulating large datasets of astronomical light curves
Author-email: Kyle Boone <kyboone@uw.edu>, Konstantin Malanchev <malanchev@cmu.edu>
License: MIT License
Project-URL: Source Code, https://github.com/lsstdesc/lcdata
Classifier: Programming Language :: Python :: 3
Classifier: License :: OSI Approved :: MIT License
Classifier: Operating System :: OS Independent
Requires-Python: >=3.6
License-File: LICENSE
Requires-Dist: astropy
Requires-Dist: h5py
Requires-Dist: numpy >=1.19.0
Requires-Dist: pyyaml
Requires-Dist: requests
Requires-Dist: tables
Requires-Dist: tqdm
Provides-Extra: docs
Requires-Dist: numpy ; extra == 'docs'
Requires-Dist: sphinx ; extra == 'docs'
Requires-Dist: sphinx-rtd-theme ; extra == 'docs'
Requires-Dist: pillow ; extra == 'docs'
Requires-Dist: numpydoc ; extra == 'docs'
Provides-Extra: download
Requires-Dist: sncosmo ; extra == 'download'
Requires-Dist: importlib-resources ; (python_version < "3.9") and extra == 'download'
Provides-Extra: test
Requires-Dist: pytest ; extra == 'test'
Requires-Dist: coverage[toml] ; extra == 'test'
Requires-Dist: pytest-cov ; extra == 'test'
